odoo10_addon_product_custom_attribute-10.0.0.0.2-nspkg.pth
odoo/addons/product_custom_attribute/README.rst
odoo/addons/product_custom_attribute/__init__.py
odoo/addons/product_custom_attribute/__manifest__.py
odoo/addons/product_custom_attribute/demo/product_attribute.xml
odoo/addons/product_custom_attribute/i18n/fr.po
odoo/addons/product_custom_attribute/i18n/it.po
odoo/addons/product_custom_attribute/i18n/product_custom_attributes.pot
odoo/addons/product_custom_attribute/migrations/7.0.0.2/post-migration.py
odoo/addons/product_custom_attribute/models/__init__.py
odoo/addons/product_custom_attribute/models/product.py
odoo/addons/product_custom_attribute/models/product_category.py
odoo/addons/product_custom_attribute/tests/__init__.py
odoo/addons/product_custom_attribute/tests/test_product_attribute.py
odoo/addons/product_custom_attribute/views/attribute_attribute.xml
odoo/addons/product_custom_attribute/views/attribute_group.xml
odoo/addons/product_custom_attribute/views/attribute_set.xml
odoo/addons/product_custom_attribute/views/product.xml
odoo/addons/product_custom_attribute/views/product_category.xml
odoo/addons/product_custom_attribute/wizard/__init__.py
odoo/addons/product_custom_attribute/wizard/open_product_by_attribute_set.py
odoo/addons/product_custom_attribute/wizard/open_product_by_attribute_set.xml
odoo/addons/product_custom_attribute/wizard/product_product.xml
odoo10_addon_product_custom_attribute-10.0.0.0.2.dist-info/METADATA
odoo10_addon_product_custom_attribute-10.0.0.0.2.dist-info/WHEEL
odoo10_addon_product_custom_attribute-10.0.0.0.2.dist-info/namespace_packages.txt
odoo10_addon_product_custom_attribute-10.0.0.0.2.dist-info/top_level.txt
odoo10_addon_product_custom_attribute-10.0.0.0.2.dist-info/RECORD
