Metadata-Version: 2.1
Name: odoo10-addon-product-custom-attribute
Version: 10.0.0.0.2
Summary: Product Custom Attributes
Home-page: https://akretion.com
Author: Akretion
License: AGPL-3
Platform: UNKNOWN
Classifier: Programming Language :: Python
Classifier: Framework :: Odoo
Classifier: License :: OSI Approved :: GNU Affero General Public License v3
Requires-Python: ~=2.7
Requires-Dist: odoo10-addon-base-custom-attribute
Requires-Dist: odoo (<10.1dev,>=10.0)
